ADS1x15/ADS1x15.py
ADS1x15/__init__.py
ADS1x15_ADC-1.2.2.dist-info/LICENCE
ADS1x15_ADC-1.2.2.dist-info/METADATA
ADS1x15_ADC-1.2.2.dist-info/WHEEL
ADS1x15_ADC-1.2.2.dist-info/top_level.txt
ADS1x15_ADC-1.2.2.dist-info/RECORD
