Metadata-Version: 2.1
Name: ADS1x15-ADC
Version: 1.2.2
Summary: Python library used for ADS1x15 analog to digital converter (ADC)
Home-page: https://github.com/chandrawi/ADS1x15-ADC
Author: Chandra Wijaya Sentosa
Author-email: chandra.w.sentosa@gmail.com
License: UNKNOWN
Project-URL: Bug Tracker, https://github.com/chandrawi/ADS1x15-ADC/issues
Platform: UNKNOWN
Classifier: Programming Language :: Python :: 2.7
Classifier: Programming Language :: Python :: 3
Classifier: License :: OSI Approved :: MIT License
Classifier: Operating System :: POSIX :: Linux
Classifier: Topic :: System :: Hardware
Classifier: Topic :: System :: Hardware :: Hardware Drivers
Requires-Python: >=2.7
License-File: LICENCE
Requires-Dist: smbus2
